glide_sdk/__init__.py
glide_sdk/examples/magic_auth_example.py
glide_sdk/examples/number_verify_example.py
glide_sdk/examples/sim_swap_example.py
glide_sdk/pyproject.toml
glide_sdk/src/glide_sdk/__init__.py
glide_sdk/src/glide_sdk/glide.py
glide_sdk/src/glide_sdk/services/magic_auth.py
glide_sdk/src/glide_sdk/services/number_verify.py
glide_sdk/src/glide_sdk/services/sim_swap.py
glide_sdk/src/glide_sdk/services/telco_finder.py
glide_sdk/src/glide_sdk/types.py
glide_sdk/src/glide_sdk/utils.py
glide_sdk/tests/test_no_mocks.py
glide_sdk-1.0.3.dist-info/METADATA
glide_sdk-1.0.3.dist-info/WHEEL
glide_sdk-1.0.3.dist-info/RECORD
